mediaify/__init__.py
mediaify/file.py
mediaify/files.py
mediaify/format.py
mediaify/py.typed
mediaify/resize.py
mediaify/utils.py
mediaify/animation/__init__.py
mediaify/animation/encode.py
mediaify/animation/exports.py
mediaify/animation/formats.py
mediaify/animation/utils.py
mediaify/audio/__init__.py
mediaify/audio/encode.py
mediaify/audio/exports.py
mediaify/audio/formats.py
mediaify/configs/__init__.py
mediaify/configs/animation.py
mediaify/configs/audio.py
mediaify/configs/base.py
mediaify/configs/codecs.py
mediaify/configs/image.py
mediaify/configs/resize.py
mediaify/configs/shared.py
mediaify/configs/video.py
mediaify/image/__init__.py
mediaify/image/encode.py
mediaify/image/exports.py
mediaify/image/formats.py
mediaify/video/__init__.py
mediaify/video/codecs.py
mediaify/video/encode.py
mediaify/video/exports.py
mediaify/video/info.py
mediaify/video/process.py
mediaify/video/summary.py
mediaify/video/thumbnail.py
mediaify-3.0.12.dist-info/LICENSE
mediaify-3.0.12.dist-info/WHEEL
mediaify-3.0.12.dist-info/METADATA
mediaify-3.0.12.dist-info/RECORD
