Metadata-Version: 2.1
Name: mediaify
Version: 3.0.12
Summary: Media encoding made simple
Author-email: Ben Brady <benbradybusiness@gmail.com>
Requires-Python: >=3.9
Classifier: Development Status :: 4 - Beta
Classifier: Intended Audience :: Developers
Classifier: Natural Language :: English
Classifier: Operating System :: OS Independent
Classifier: License :: OSI Approved :: MIT License
Classifier: Programming Language :: Python
Classifier: Programming Language :: Python :: 3.9
Classifier: Programming Language :: Python :: 3.10
Classifier: Programming Language :: Python :: 3.11
Classifier: Topic :: Multimedia
Classifier: Topic :: Multimedia :: Graphics
Classifier: Topic :: Multimedia :: Graphics :: Graphics Conversion
Classifier: Topic :: Multimedia :: Video
Classifier: Topic :: Multimedia :: Video :: Conversion
Classifier: Typing :: Typed
Requires-Dist: python-ffmpeg>=2.0.4
Requires-Dist: MediaInfo>=0.0.9
Requires-Dist: pillow>=9.5.0
Requires-Dist: python_magic>=0.4.27
Requires-Dist: python-magic-bin; sys_platform == 'win32'
Requires-Dist: numexpr
Requires-Dist: libmagic ; extra == "docs"
Requires-Dist: mypy ==0.982 ; extra == "test"
Requires-Dist: pytest >=7.1.3,<8.0.0 ; extra == "test"
Requires-Dist: black == 23.1.0 ; extra == "test"
Project-URL: Documentation, https://mediaify.readthedocs.io/
Project-URL: Source, https://github.com/Ben-Brady/mediaify
Provides-Extra: docs
Provides-Extra: test
